HABApp/__check_dependency_packages__.py
HABApp/__cmd_args__.py
HABApp/__debug_info__.py
HABApp/__init__.py
HABApp/__main__.py
HABApp/__setup_packages__.py
HABApp/__splash_screen__.py
HABApp/__version__.py
HABApp/py.typed
HABApp/config/__init__.py
HABApp/config/config.py
HABApp/config/debug.py
HABApp/config/errors.py
HABApp/config/loader.py
HABApp/config/platform_defaults.py
HABApp/config/logging/__init__.py
HABApp/config/logging/buffered_logger.py
HABApp/config/logging/config.py
HABApp/config/logging/default_logfile.py
HABApp/config/logging/handler.py
HABApp/config/logging/queue_handler.py
HABApp/config/logging/utils.py
HABApp/config/models/__init__.py
HABApp/config/models/application.py
HABApp/config/models/directories.py
HABApp/config/models/habapp.py
HABApp/config/models/location.py
HABApp/config/models/mqtt.py
HABApp/config/models/openhab.py
HABApp/core/__init__.py
HABApp/core/asyncio.py
HABApp/core/errors.py
HABApp/core/logger.py
HABApp/core/shutdown.py
HABApp/core/wrapper.py
HABApp/core/connections/__init__.py
HABApp/core/connections/_definitions.py
HABApp/core/connections/base_connection.py
HABApp/core/connections/base_plugin.py
HABApp/core/connections/connection_task.py
HABApp/core/connections/manager.py
HABApp/core/connections/plugin_callback.py
HABApp/core/connections/status_transitions.py
HABApp/core/connections/plugins/__init__.py
HABApp/core/connections/plugins/auto_reconnect.py
HABApp/core/connections/plugins/state_to_event.py
HABApp/core/const/__init__.py
HABApp/core/const/const.py
HABApp/core/const/hints.py
HABApp/core/const/installation.py
HABApp/core/const/json.py
HABApp/core/const/log.py
HABApp/core/const/loop.py
HABApp/core/const/topics.py
HABApp/core/const/yml.py
HABApp/core/events/__init__.py
HABApp/core/events/events.py
HABApp/core/events/habapp_events.py
HABApp/core/events/filter/__init__.py
HABApp/core/events/filter/event.py
HABApp/core/events/filter/groups.py
HABApp/core/events/filter/habapp_events.py
HABApp/core/events/filter/no_filter.py
habapp-25.12.0.dist-info/licenses/LICENSE
habapp-25.12.0.dist-info/METADATA
habapp-25.12.0.dist-info/WHEEL
habapp-25.12.0.dist-info/entry_points.txt
habapp-25.12.0.dist-info/top_level.txt
habapp-25.12.0.dist-info/RECORD
