Metadata-Version: 2.4
Name: HABApp
Version: 25.12.0
Summary: Easy automation with MQTT and/or openHAB. Create home automation rules in python.
Home-page: https://github.com/spacemanspiff2007/HABApp
Author: spaceman_spiff
Project-URL: Documentation, https://habapp.readthedocs.io/
Project-URL: GitHub, https://github.com/spacemanspiff2007/HABApp
Keywords: mqtt,openhab,habapp,home automation
Classifier: Development Status :: 4 - Beta
Classifier: Framework :: AsyncIO
Classifier: License :: OSI Approved :: Apache Software License
Classifier: Operating System :: OS Independent
Classifier: Programming Language :: Python :: 3.11
Classifier: Programming Language :: Python :: 3.12
Classifier: Programming Language :: Python :: 3.13
Classifier: Programming Language :: Python :: 3.14
Classifier: Programming Language :: Python :: 3 :: Only
Classifier: Topic :: Home Automation
Requires-Python: >=3.11
License-File: LICENSE
Requires-Dist: aiohttp==3.13.2
Requires-Dist: pydantic==2.12.5
Requires-Dist: bidict==0.23.1
Requires-Dist: watchfiles==1.1.1
Requires-Dist: ujson==5.11.0
Requires-Dist: aiomqtt==2.4.0
Requires-Dist: eascheduler==0.2.7
Requires-Dist: immutables==0.21
Requires-Dist: easyconfig==0.4.2
Requires-Dist: stack_data==0.6.3
Requires-Dist: colorama==0.4.6
Requires-Dist: fastnumbers==5.1.1
Requires-Dist: geopy==2.4.1
Requires-Dist: typing-extensions==4.15.0
Requires-Dist: aiohttp-sse-client==0.2.1
Requires-Dist: javaproperties==0.8.2
Dynamic: author
Dynamic: classifier
Dynamic: description
Dynamic: description-content-type
Dynamic: home-page
Dynamic: keywords
Dynamic: license-file
Dynamic: project-url
Dynamic: requires-dist
Dynamic: requires-python
Dynamic: summary
